LICENSE
MANIFEST.in
README.rst
setup.py
wagtail_eventcalendar/__init__.py
wagtail_eventcalendar/admin.py
wagtail_eventcalendar/apps.py
wagtail_eventcalendar/managers.py
wagtail_eventcalendar/models.py
wagtail_eventcalendar/tests.py
wagtail_eventcalendar/views.py
wagtail_eventcalendar/wagtail_hooks.py
wagtail_eventcalendar.egg-info/PKG-INFO
wagtail_eventcalendar.egg-info/SOURCES.txt
wagtail_eventcalendar.egg-info/dependency_links.txt
wagtail_eventcalendar.egg-info/requires.txt
wagtail_eventcalendar.egg-info/top_level.txt
wagtail_eventcalendar/__pycache__/__init__.cpython-36.pyc
wagtail_eventcalendar/__pycache__/admin.cpython-36.pyc
wagtail_eventcalendar/__pycache__/managers.cpython-36.pyc
wagtail_eventcalendar/__pycache__/models.cpython-36.pyc
wagtail_eventcalendar/__pycache__/wagtail_hooks.cpython-36.pyc
wagtail_eventcalendar/docs/Makefile
wagtail_eventcalendar/docs/source/api.rst
wagtail_eventcalendar/docs/source/changelog.rst
wagtail_eventcalendar/docs/source/conf.py
wagtail_eventcalendar/docs/source/customising.rst
wagtail_eventcalendar/docs/source/getting-started.rst
wagtail_eventcalendar/docs/source/index.rst
wagtail_eventcalendar/docs/source/internationalisation.rst
wagtail_eventcalendar/docs/source/requirements.txt
wagtail_eventcalendar/docs/source/roadmap.rst
wagtail_eventcalendar/docs/source/syncing.rst
wagtail_eventcalendar/locale/af/LC_MESSAGES/django.mo
wagtail_eventcalendar/locale/af/LC_MESSAGES/django.po
wagtail_eventcalendar/migrations/0001_initial.py
wagtail_eventcalendar/migrations/__init__.py
wagtail_eventcalendar/migrations/__pycache__/0001_initial.cpython-36.pyc
wagtail_eventcalendar/migrations/__pycache__/__init__.cpython-36.pyc
wagtail_eventcalendar/static/wagtail_eventcalendar/css/all.css
wagtail_eventcalendar/static/wagtail_eventcalendar/css/bootstrap.min.css
wagtail_eventcalendar/static/wagtail_eventcalendar/css/custom.css
wagtail_eventcalendar/static/wagtail_eventcalendar/css/fullcalendar.min.css
wagtail_eventcalendar/static/wagtail_eventcalendar/css/kerk.css
wagtail_eventcalendar/static/wagtail_eventcalendar/js/bootstrap.bundle.min.js
wagtail_eventcalendar/static/wagtail_eventcalendar/js/fullcalendar.min.js
