Metadata-Version: 2.1
Name: wagtail-eventcalendar
Version: 0.1.1
Summary: A simple calendar app built for Wagtail CMS and Django
Home-page: https://gitlab.com/dfmeyer/wagtail_eventcalendar
Author: Daniel F. Meyer
Author-email: me3064@gmail.com
License: MIT
Project-URL: Bug Tracker, https://gitlab.com/dfmeyer/wagtail_eventcalendar/issues
Project-URL: Documentation, https://wagtail-eventcalendar.readthedocs.io/en/latest/
Project-URL: Source Code, https://gitlab.com/dfmeyer/wagtail_eventcalendar
Keywords: Django,Wagtail,calendar,events
Platform: UNKNOWN
Requires-Python: >=3.5
